Metadata-Version: 2.1
Name: primed-avro
Version: 0.0.6
Summary: A python package that provides functionality to interface with the Confluent Schema Registtry
Home-page: https://gitlab.com/primedio/primed-avro
Author: Matthijs van der Kroon
Author-email: matthijs@primed.io
License: BSD
Download-URL: https://gitlab.com/primedio/primed-avro/tarball/0.0.6
Platform: UNKNOWN
Classifier: Development Status :: 3 - Alpha
Classifier: Intended Audience :: Developers
Classifier: Programming Language :: Python :: 3
License-File: LICENSE.md
